openly/__init__.py
openly/api.py
openly/cloud.py
openly/const.py
openly/devices/__init__.py
openly/devices/base_device.py
openly/devices/dimmer.py
openly/devices/hub.py
openly/devices/leak.py
openly/devices/lock.py
openly/devices/switch.py
openly/devices/thermostat.py
openly/exceptions.py
openly/util.py
openly_core-0.2.2.dist-info/LICENSE
openly_core-0.2.2.dist-info/METADATA
openly_core-0.2.2.dist-info/WHEEL
openly_core-0.2.2.dist-info/RECORD
